MANIFEST.in
README.md
setup.py
sudokutools/__init__.py
sudokutools/__main__.py
sudokutools/analyze.py
sudokutools/dlx.py
sudokutools/generate.py
sudokutools/shell.py
sudokutools/solve.py
sudokutools/solvers.py
sudokutools/sudoku.py
sudokutools.egg-info/PKG-INFO
sudokutools.egg-info/SOURCES.txt
sudokutools.egg-info/dependency_links.txt
sudokutools.egg-info/entry_points.txt
sudokutools.egg-info/top_level.txt
sudokutools/tests/__init__.py
sudokutools/tests/constants.py
sudokutools/tests/test_analyze.py
sudokutools/tests/test_generate.py
sudokutools/tests/test_shell.py
sudokutools/tests/test_solve.py
sudokutools/tests/test_solvers.py
sudokutools/tests/test_sudoku.py